cbc_sdk/__init__.py
cbc_sdk/base.py
cbc_sdk/connection.py
cbc_sdk/credentials.py
cbc_sdk/errors.py
cbc_sdk/helpers.py
cbc_sdk/live_response_api.py
cbc_sdk/rest_api.py
cbc_sdk/utils.py
cbc_sdk/winerror.py
cbc_sdk/audit_remediation/__init__.py
cbc_sdk/audit_remediation/base.py
cbc_sdk/audit_remediation/differential.py
cbc_sdk/audit_remediation/models/device_summary.yaml
cbc_sdk/audit_remediation/models/differential.yaml
cbc_sdk/audit_remediation/models/facet.yaml
cbc_sdk/audit_remediation/models/result.yaml
cbc_sdk/audit_remediation/models/run.yaml
cbc_sdk/audit_remediation/models/template.yaml
cbc_sdk/cache/__init__.py
cbc_sdk/cache/lru.py
cbc_sdk/credential_providers/__init__.py
cbc_sdk/credential_providers/aws_sm_credential_provider.py
cbc_sdk/credential_providers/default.py
cbc_sdk/credential_providers/environ_credential_provider.py
cbc_sdk/credential_providers/file_credential_provider.py
cbc_sdk/credential_providers/keychain_credential_provider.py
cbc_sdk/credential_providers/registry_credential_provider.py
cbc_sdk/endpoint_standard/__init__.py
cbc_sdk/endpoint_standard/base.py
cbc_sdk/endpoint_standard/recommendation.py
cbc_sdk/endpoint_standard/usb_device_control.py
cbc_sdk/endpoint_standard/models/deviceInfo.yaml
cbc_sdk/endpoint_standard/models/enriched_event_facet.yaml
cbc_sdk/endpoint_standard/models/policyInfo.yaml
cbc_sdk/endpoint_standard/models/recommendation.yaml
cbc_sdk/endpoint_standard/models/recommendation_application.yaml
cbc_sdk/endpoint_standard/models/recommendation_impact.yaml
cbc_sdk/endpoint_standard/models/recommendation_new_rule.yaml
cbc_sdk/endpoint_standard/models/recommendation_workflow.yaml
cbc_sdk/endpoint_standard/models/usbDevice.yaml
cbc_sdk/endpoint_standard/models/usbDeviceApproval.yaml
cbc_sdk/endpoint_standard/models/usbDeviceBlock.yaml
cbc_sdk/enterprise_edr/__init__.py
cbc_sdk/enterprise_edr/auth_events.py
cbc_sdk/enterprise_edr/threat_intelligence.py
cbc_sdk/enterprise_edr/ubs.py
carbon_black_cloud_sdk-1.5.8.dist-info/LICENSE
carbon_black_cloud_sdk-1.5.8.dist-info/METADATA
carbon_black_cloud_sdk-1.5.8.dist-info/WHEEL
carbon_black_cloud_sdk-1.5.8.dist-info/top_level.txt
carbon_black_cloud_sdk-1.5.8.dist-info/RECORD
