Metadata-Version: 2.1
Name: carbon-black-cloud-sdk
Version: 1.5.8
Summary: Carbon Black Cloud Python SDK
Home-page: https://github.com/carbonblack/carbon-black-cloud-sdk-python
Author: Carbon Black
Author-email: cb-developer-network@vmware.com
License: MIT
Platform: any
Classifier: Environment :: Web Environment
Classifier: Intended Audience :: Developers
Classifier: Intended Audience :: System Administrators
Classifier: Operating System :: OS Independent
Classifier: Programming Language :: Python :: 3.8
Classifier: Programming Language :: Python :: 3.9
Classifier: Programming Language :: Python :: 3.10
Classifier: Programming Language :: Python :: 3.11
Classifier: Programming Language :: Python :: 3.12
Classifier: Topic :: Security
Classifier: Topic :: Software Development :: Libraries :: Python Modules
License-File: LICENSE
Requires-Dist: requests
Requires-Dist: pyyaml
Requires-Dist: python-dateutil
Requires-Dist: schema
Requires-Dist: solrq
Requires-Dist: validators
Requires-Dist: jsonschema
Requires-Dist: boto3
Requires-Dist: keyring ; platform_system == "Darwin"
Requires-Dist: backports-datetime-fromisoformat ==2.0.1 ; python_version < "3.11"
Provides-Extra: test
Requires-Dist: pytest ==7.2.1 ; extra == 'test'
Requires-Dist: pymox ==1.0.0 ; extra == 'test'
Requires-Dist: coverage ==6.5.0 ; extra == 'test'
Requires-Dist: flake8 ==5.0.4 ; extra == 'test'
Requires-Dist: flake8-colors ==0.1.9 ; extra == 'test'
Requires-Dist: flake8-docstrings ==1.7.0 ; extra == 'test'
Requires-Dist: pre-commit >=2.15.0 ; extra == 'test'
Requires-Dist: requests-mock ==1.10.0 ; extra == 'test'
